chariotCore/__init__.py
chariotCore/main.py
chariotCore/tasks.py
chariotCore/templates.py
chariotCore/tools.py
chariotCore/res/Dockerfile
chariotCore/res/__init__.py
chariotCore/res/config.ini
chariotCore/res/icon.png
chariotCore/res/plugin.spec.yaml
chariotCore/res/requirements.txt
chariotCore/res/SDK/__init__.py
chariotCore/res/SDK/base.py
chariotCore/res/SDK/chariot.py
chariotCore/res/SDK/cli.py
chariotCore/res/SDK/models.py
chariotCore/res/SDK/subassembly.py
chariotCore/res/SDK/web.py
chariot_sdk-1.3.4.dist-info/METADATA
chariot_sdk-1.3.4.dist-info/WHEEL
chariot_sdk-1.3.4.dist-info/entry_points.txt
chariot_sdk-1.3.4.dist-info/top_level.txt
chariot_sdk-1.3.4.dist-info/RECORD
