Metadata-Version: 2.1
Name: chariot-sdk
Version: 1.3.4
Summary: Chariot plugin maker
Home-page: https://pypi.org/
Author: chariot
Author-email: chariot@example.com
License: MIT
Requires-Python: >=3
Requires-Dist: pydantic
Requires-Dist: argparse
Requires-Dist: jinja2
Requires-Dist: pyyaml
Requires-Dist: fastapi
Requires-Dist: uvicorn
Requires-Dist: requests
Requires-Dist: python-multipart
Requires-Dist: docker
Requires-Dist: psutil
